{"GX76mJJOviF37l4wr7cGDw==":"marvel-superheroes-pic-620x330.jpg","Uz4TUpoReR6KG/sMvp40sg==":"marvelmap-1491x618.png","ghDW7iSP0z5AsoZJR3/vBw==":"word%20cloud%20all-676x676.jpg","QNMfPOPZ800y/ixBRTGbbg==":"man%20word%20cloud-676x676.jpg","k+yQyxzNo1GK39eFtzJ2tw==":"women%20word%20cloud-676x676.jpg","5NKIpLfBCnqzIBanON1GPw==":"word%20cloud%20all-707x707.jpg","lxb9CIec5Ml3QtC6YxcbpQ==":"man%20word%20cloud-707x707.jpg","EeoGbH0QerTeWJr9QQCR0g==":"women%20word%20cloud-652x652.jpg","J5bnxnLgJ9ikpmsqeLGawA==":"bar%20graph%20he%20vs%20she-1024x316.jpg","bybKwimUg77pCkxYJZnzrg==":"better%20bubble%20map-860x842.jpg","K8rM4bpp9hYcRDBbAbwIcQ==":"bar%20graph%20he%20vs%20she-1332x411.jpg","KyHB33F6RcpYntykrI4UGw==":"captain%20marvel%20powers%20-%20sheet1.csv-877x477.png","NFg1OcYRU8xF3EUU7OwhCA==":"captain%20marvel%20powers%20-%20sheet1.csv-543x426.png","7MH7+nb9Q5ojeJDrphlGDA==":"thanos%20powers%20-%20sheet1.csv-581x441.png","Y0pWr4kfsVBH/bKitPAg6w==":"timeline-1465x728.png","ISawslqM2AR/I43I7L4HPw==":"labor-force-participation-of-women-in-the-us-1955-2005-436x241.png","41QzqhHWjjP+Vs/WWccFeA==":"660px-women_serving_in_the_u.s._house_of_representatives_by_party_through-2019-436x305.png","fDd8s5kpn3uyd6wfK4/O4g==":"captain-america-cover.jpg","FWt7TDMZjwKDmy1oiNlxiw==":"red-skull.jpg","vJB9QBbCtu1Yw2dCYN9rXg==":"magneto.jpg","uQ+29v0FHEWO6HsIGAHtWA==":"dr.-doom.jpg","2LjiTx2nLLfN5/QO0T8V6g==":"dr.-doom-1.jpg","2825aixNPjTIgxckfGtghg==":"new-york.jpg","R3yCjAXOIgzvpQk8roItMA==":"new-york-1.jpg","l+VU4H7lyRrj1nSWvg/B/g==":"invisible-woman.jpg","H05hxLUuninKJDlv08xheg==":"labor-force-participation-of-women-in-the-us-1955.png","S84BUYWLAoafjfZiFcfyfw==":"660px-women-serving-in-the-u.s.-house-of-representatives-by-party-through-2019.png"}